apsystems_api/__init__.py
apsystems_api-0.1.15.dist-info/LICENSE
apsystems_api-0.1.15.dist-info/METADATA
apsystems_api-0.1.15.dist-info/WHEEL
apsystems_api-0.1.15.dist-info/RECORD
